{
  "title": "TRAIN MINER",
  "description": "All aboard for endless mining fun in Train Miner – expand, upgrade, and dominate the tracks! Train Miner is a unique and addictive resource-mining game where you control a train on a looping track, automatically harvesting valuable resources nearby. As you mine, the track expands, unlocking new areas and boosting your profits. Sell your resources, upgrade your train, and watch it grow longer and faster with each run! With a perfect blend of strategy, automation, and satisfying progression, Train Miner keeps you hooked as you build the ultimate mining empire on rails. So hop on board, mine, and expand your railway empire in Train Miner!",
  "iframe_url": "https://play.famobi.com/train-miner",
  "preview_image": "https://img.cdn.famobi.com/portal/html5games/images/tmp/180/TrainMinerTeaser.jpg?v=0.2-aa02f4cb",
  "categories": [
    "Multiplayer"
  ],
  "url": "https://html5games.com/Game/Train-Miner/0d52d629-a40a-4a95-b13a-7f951a3f50b1",
  "scraped_at": "2025-07-13T16:08:30.991644"
}