{
  "url": "https://html5games.com/Game/Text-Twist-2/40935b5f-cfef-4ac2-9179-549869282f4b",
  "title": "TEXT TWIST 2",
  "description": "Let's twist! Get ready for some word-finding fun in Text Twist 2! Look at the jumbled letters and find all the word combinations. You need at least one six-letter word to move on to the next round. Use the Twist button to rearrange the letters and find more combinations. Test your vocabulary skills and try to score as many points as possible. How many rounds can you beat?",
  "iframe_url": "https://play.famobi.com/text-twist-2",
  "preview_image": "https://img.cdn.famobi.com/portal/html5games/images/tmp/180/TextTwist2Teaser.jpg?v=0.2-aa02f4cb",
  "categories": [
    "Puzzle"
  ],
  "scraped_at": "2025-07-12T23:06:28.927555",
  "category": "Puzzle"
}