{
  "url": "https://html5games.com/Game/7-Words/fe28ef90-9fd8-4642-b663-45b784ecab42",
  "title": "7 WORDS",
  "description": "If you like puzzles and crosswords, this is the perfect game for you! Look at the tiles and tap on them in the correct order to unscramble the word. You can sort the pieces alphabetically or randomly and use a hint if you are stuck. Can you complete all 777 levels of this challenging word game?",
  "iframe_url": "https://play.famobi.com/7-words",
  "preview_image": "https://img.cdn.famobi.com/portal/html5games/images/tmp/180/7WordsTeaser.jpg?v=0.2-aa02f4cb",
  "categories": [
    "Puzzle"
  ],
  "scraped_at": "2025-07-12T22:45:06.419614",
  "category": "Puzzle"
}